boxmot/__init__.py
boxmot/configs/datasets/MOT17-ablation.yaml
boxmot/configs/datasets/MOT20-ablation.yaml
boxmot/configs/datasets/SportsMOT.yaml
boxmot/configs/datasets/custom.yaml
boxmot/configs/datasets/dancetrack-ablation.yaml
boxmot/configs/datasets/vizdrone-ablation.yaml
boxmot/configs/trackers/__init__.py
boxmot/configs/trackers/boosttrack.yaml
boxmot/configs/trackers/botsort.yaml
boxmot/configs/trackers/bytetrack.yaml
boxmot/configs/trackers/deepocsort.yaml
boxmot/configs/trackers/hybridsort.yaml
boxmot/configs/trackers/imprassoc.yaml
boxmot/configs/trackers/ocsort.yaml
boxmot/configs/trackers/strongsort.yaml
boxmot/detectors/__init__.py
boxmot/detectors/detector.py
boxmot/detectors/rtdetr.py
boxmot/detectors/ultralytics.py
boxmot/detectors/yolox.py
boxmot/engine/__init__.py
boxmot/engine/cli.py
boxmot/engine/evaluator.py
boxmot/engine/export.py
boxmot/engine/results.py
boxmot/engine/tracker.py
boxmot/engine/tuner.py
boxmot/motion/__init__.py
boxmot/motion/cmc/__init__.py
boxmot/motion/cmc/base_cmc.py
boxmot/motion/cmc/ecc.py
boxmot/motion/cmc/orb.py
boxmot/motion/cmc/sift.py
boxmot/motion/cmc/sof.py
boxmot/motion/kalman_filters/__init__.py
boxmot/motion/kalman_filters/aabb/__init__.py
boxmot/motion/kalman_filters/aabb/base_kalman_filter.py
boxmot/motion/kalman_filters/aabb/xyah_kf.py
boxmot/motion/kalman_filters/aabb/xysr_kf.py
boxmot/motion/kalman_filters/aabb/xywh_kf.py
boxmot/motion/kalman_filters/obb/__init__.py
boxmot/motion/kalman_filters/obb/xywha_kf.py
boxmot/postprocessing/__init__.py
boxmot/postprocessing/gbrc.py
boxmot/postprocessing/gsi.py
boxmot/reid/__init__.py
boxmot/reid/backbones/__init__.py
boxmot/reid/backbones/hacnn.py
boxmot/reid/backbones/mlfn.py
boxmot/reid/backbones/mobilenetv2.py
boxmot/reid/backbones/osnet.py
boxmot/reid/backbones/osnet_ain.py
boxmot/reid/backbones/resnet.py
boxmot/reid/backbones/clip/__init__.py
boxmot/reid/backbones/clip/make_model.py
boxmot/reid/backbones/clip/make_model_clipreid.py
boxmot-16.0.8.dist-info/METADATA
boxmot-16.0.8.dist-info/WHEEL
boxmot-16.0.8.dist-info/entry_points.txt
boxmot-16.0.8.dist-info/licenses/LICENSE
boxmot-16.0.8.dist-info/RECORD
