Metadata-Version: 2.4
Name: boxmot
Version: 16.0.8
Summary: BoxMOT: pluggable SOTA tracking modules for segmentation, object detection and pose estimation models
Author: Mikel Broström
License: AGPL-3.0
License-File: LICENSE
Keywords: AI,DL,ML,YOLO,deep-learning,machine-learning,tracking,tracking-by-detection,vision
Classifier: Development Status :: 4 - Beta
Classifier: Intended Audience :: Developers
Classifier: Intended Audience :: Education
Classifier: Intended Audience :: Science/Research
Classifier: License :: OSI Approved :: GNU Affero General Public License v3 or later (AGPLv3+)
Classifier: Programming Language :: Python :: 3
Classifier: Programming Language :: Python :: 3.9
Classifier: Programming Language :: Python :: 3.10
Classifier: Programming Language :: Python :: 3.11
Classifier: Programming Language :: Python :: 3.12
Classifier: Topic :: Scientific/Engineering
Classifier: Topic :: Scientific/Engineering :: Artificial Intelligence
Classifier: Topic :: Scientific/Engineering :: Image Processing
Classifier: Topic :: Scientific/Engineering :: Image Recognition
Classifier: Topic :: Software Development
Requires-Python: <3.13,>=3.9
Requires-Dist: click>=8.1.8
Requires-Dist: filterpy<2.0.0,>=1.4.5
Requires-Dist: ftfy<7.0.0,>=6.1.3
Requires-Dist: gdown<6.0.0,>=5.1.0
Requires-Dist: lapx<1.0.0,>=0.5.5
Requires-Dist: loguru<1.0.0,>=0.7.2
Requires-Dist: numpy
Requires-Dist: opencv-python<5.0.0,>=4.7.0
Requires-Dist: pandas<3.0.0,>=2.0.0
Requires-Dist: regex<2025.0.0,>=2024.0.0
Requires-Dist: scikit-learn<2.0.0,>=1.3.0
Requires-Dist: torch<3.0.0,>=2.2.1
Requires-Dist: torchvision<1.0.0,>=0.17.1
Requires-Dist: yacs<1.0.0,>=0.1.8
Provides-Extra: evolve
Requires-Dist: bayesian-optimization==2.0.4; extra == 'evolve'
Requires-Dist: optuna==3.5.0; extra == 'evolve'
Requires-Dist: plotly==5.19.0; extra == 'evolve'
Requires-Dist: pydantic==2.7.2; extra == 'evolve'
Requires-Dist: ray[tune]==2.49.2; extra == 'evolve'
Provides-Extra: onnx
Requires-Dist: onnx<1.19,>=1.16.1; extra == 'onnx'
Requires-Dist: onnxruntime>=1.18.1; extra == 'onnx'
Requires-Dist: onnxscript>=0.1.0; extra == 'onnx'
Requires-Dist: onnxslim>=0.1.67; extra == 'onnx'
Provides-Extra: openvino
Requires-Dist: openvino>=2025.2.0; extra == 'openvino'
Provides-Extra: tflite
Requires-Dist: ai-edge-litert==1.2.0; (python_version < '3.13' and sys_platform == 'linux') and extra == 'tflite'
Requires-Dist: flatbuffers>=23.1.21; (python_version < '3.13' and (sys_platform == 'linux' or sys_platform == 'win32')) and extra == 'tflite'
Requires-Dist: ml-dtypes==0.5.1; (python_version < '3.13' and (sys_platform == 'linux' or sys_platform == 'win32')) and extra == 'tflite'
Requires-Dist: onnx-graphsurgeon>=0.3.26; (python_version < '3.13' and (sys_platform == 'linux' or sys_platform == 'win32')) and extra == 'tflite'
Requires-Dist: onnx2tf>=1.18.0; (python_version < '3.13' and (sys_platform == 'linux' or sys_platform == 'win32')) and extra == 'tflite'
Requires-Dist: onnx==1.17.0; (python_version < '3.13' and (sys_platform == 'linux' or sys_platform == 'win32')) and extra == 'tflite'
Requires-Dist: onnxruntime==1.18.1; (python_version < '3.13' and (sys_platform == 'linux' or sys_platform == 'win32')) and extra == 'tflite'
Requires-Dist: onnxsim==0.4.33; (python_version < '3.13' and (sys_platform == 'linux' or sys_platform == 'win32')) and extra == 'tflite'
Requires-Dist: onnxslim>=0.1.31; (python_version < '3.13' and (sys_platform == 'linux' or sys_platform == 'win32')) and extra == 'tflite'
Requires-Dist: psutil==5.9.5; (python_version < '3.13' and (sys_platform == 'linux' or sys_platform == 'win32')) and extra == 'tflite'
Requires-Dist: simple-onnx-processing-tools; (python_version < '3.13' and (sys_platform == 'linux' or sys_platform == 'win32')) and extra == 'tflite'
Requires-Dist: sng4onnx>=1.0.1; (python_version < '3.13' and (sys_platform == 'linux' or sys_platform == 'win32')) and extra == 'tflite'
Requires-Dist: tensorflow==2.19.0; (python_version < '3.13' and (sys_platform == 'linux' or sys_platform == 'win32')) and extra == 'tflite'
Requires-Dist: tf-keras==2.19.0; (python_version < '3.13' and (sys_platform == 'linux' or sys_platform == 'win32')) and extra == 'tflite'
Provides-Extra: yolo
Requires-Dist: ultralytics>=3.8.200; extra == 'yolo'
Requires-Dist: yolox==0.3.0; extra == 'yolo'
